jinja_yaml_magic/__init__.py
jinja_yaml_magic/jinja_yaml_magic.py
jinja_yaml_magic-0.1.2.dist-info/LICENSE
jinja_yaml_magic-0.1.2.dist-info/METADATA
jinja_yaml_magic-0.1.2.dist-info/WHEEL
jinja_yaml_magic-0.1.2.dist-info/top_level.txt
jinja_yaml_magic-0.1.2.dist-info/RECORD
