Metadata-Version: 2.1
Name: jinja-yaml-magic
Version: 0.1.2
Summary: Support Jinja2 and YAML in IPython/Jupyter notebooks
Home-page: https://github.com/nopdotcom/jupyter-jinja-yaml-magic
Author: Jay Carlson
Author-email: nop@nop.com
License: MIT
Keywords: jupyter,ipython,yaml,jinja,jinja2
Platform: UNKNOWN
Classifier: Programming Language :: Python :: 3
Classifier: Programming Language :: Python :: 2
Classifier: License :: OSI Approved :: MIT License
Classifier: Operating System :: OS Independent
Requires-Dist: PyYAML
Requires-Dist: jinja2
Requires-Dist: ipython (>=1.0)
